data/api_examples.json
data/dataset.zip
data/llama3-josh-toolwoz-for-KTO.zip
data/testListFile.json
data/tools.json
data/valListFile.json
data/valid_api_defs.json
db/attraction-dbase.db
db/attraction_db.json
db/bus-dbase.db
db/bus_db.json
db/hospital-dbase.db
db/hospital_db.json
db/hotel-dbase.db
db/hotel_db.json
db/police_db.json
db/restaurant-dbase.db
db/restaurant_db.json
db/taxi-dbase.db
db/taxi_db.json
db/train-dbase.db
db/train_db.json
josh_train/__init__.py
josh_train/_version.py
josh_train/async_josh.py
josh_train/build_apis.py
josh_train/config.py
josh_train/josh.py
josh_train/main.py
josh_train/training_fnames.json
josh_train/utils.py
josh_train/agents/fc_agent.py
josh_train/agents/react_agent.py
josh_train/conversation_types/conversation_state.py
josh_train/conversation_types/conversation_state_pref_tree.py
josh_train/finetune/finetune_agent.py
josh_train/finetune/kto_ft.py
josh_train/finetune/sft_agent.py
josh_train/finetune/sft_agent_final_mod.py
josh_train/finetune/sft_agent_successful.py
josh_train/users/base_user_simulator.py
josh_train/users/goal_user_simulator.py
josh_train/users/guide_user_simulator.py
josh_train/users/script_user_simulator.py
prompts/prompts.yaml
tau-bench-eval/LICENSE
tau-bench-eval/README.md
tau-bench-eval/auto_error_identification.py
tau-bench-eval/run.py
tau-bench-eval/setup.py
tau-bench-eval/tau_bench/__init__.py
tau-bench-eval/tau_bench/types.py
tau-bench-eval/tau_bench/agents/__init__.py
tau-bench-eval/tau_bench/agents/base.py
tau-bench-eval/tau_bench/agents/chat_react_agent.py
tau-bench-eval/tau_bench/agents/josh_chat_react_agent.py
tau-bench-eval/tau_bench/agents/josh_tool_calling_agent.py
tau-bench-eval/tau_bench/agents/tool_calling_agent.py
tau-bench-eval/tau_bench/envs/__init__.py
tau-bench-eval/tau_bench/envs/base.py
tau-bench-eval/tau_bench/envs/tool.py
tau-bench-eval/tau_bench/envs/user.py
tau-bench-eval/tau_bench/envs/airline/__init__.py
tau-bench-eval/tau_bench/envs/airline/env.py
josh_train-0.1.4.dist-info/LICENSE
josh_train-0.1.4.dist-info/METADATA
josh_train-0.1.4.dist-info/WHEEL
josh_train-0.1.4.dist-info/top_level.txt
josh_train-0.1.4.dist-info/RECORD
