Metadata-Version: 2.2
Name: josh_train
Version: 0.1.4
Summary: A simulation training framework
Home-page: https://github.com/josh-llm-simulation-training
Author: blattimer
Author-email: blattimer@asapp.com
Classifier: Programming Language :: Python :: 3
Classifier: License :: OSI Approved :: MIT License
Classifier: Operating System :: OS Independent
Requires-Python: >=3.8
License-File: LICENSE
Requires-Dist: python-dotenv
Requires-Dist: colorama
Requires-Dist: openai
Requires-Dist: pyyaml
Requires-Dist: datasets
Requires-Dist: accelerate
Requires-Dist: transformers
Requires-Dist: numpy
Requires-Dist: pandas
Requires-Dist: trl
Requires-Dist: torch
Requires-Dist: deepsig
Requires-Dist: tiktoken
Dynamic: author
Dynamic: author-email
Dynamic: classifier
Dynamic: description
Dynamic: description-content-type
Dynamic: home-page
Dynamic: requires-dist
Dynamic: requires-python
Dynamic: summary
